biovoronoi/__init__.py
biovoronoi/_version.py
biovoronoi/cli.py
biovoronoi/core.py
test/__init__.py
test/test_biopython.py
test/test_core.py
test/test_scipy_voronoi.py
biovoronoi-0.2.0.dist-info/METADATA
biovoronoi-0.2.0.dist-info/WHEEL
biovoronoi-0.2.0.dist-info/top_level.txt
biovoronoi-0.2.0.dist-info/RECORD
